djangocms_algolia/__init__.py
djangocms_algolia/apps.py
djangocms_algolia/index.py
djangocms_algolia/signals.py
djangocms_algolia/utils/__init__.py
djangocms_algolia/utils/proxy_checker.py
djangocms_algolia/utils/render.py
djangocms_algolia-1.5.0.1.dist-info/LICENSE
djangocms_algolia-1.5.0.1.dist-info/METADATA
djangocms_algolia-1.5.0.1.dist-info/WHEEL
djangocms_algolia-1.5.0.1.dist-info/top_level.txt
djangocms_algolia-1.5.0.1.dist-info/RECORD
