Metadata-Version: 2.1
Name: djangocms-algolia
Version: 1.5.0.1
Summary: UNKNOWN
Home-page: https://gitlab.com/victor.yunenko/djangocms-algolia
Author: Victor Yunenko
Author-email: victor@what.digital
License: UNKNOWN
Platform: UNKNOWN
Requires-Dist: django (>=2.2)
Requires-Dist: django-cms (>=3.7)
Requires-Dist: algoliasearch-django
Requires-Dist: aldryn-search
Requires-Dist: beautifulsoup4
Requires-Dist: django-standard-form (==1.1.1)
